{
  "name": "Real Strategies",
  "schema_name": "real_strategies",
  "overview": "The Real Strategies data connector is a powerful tool that allows marketers to connect their marketing data from various sources and platforms into one centralized dashboard. This connector offers seamless integration and easy access to all your marketing metrics, providing valuable insights and actionable data for more informed decision-making.",
  "body": "Designed to streamline marketing analytics, the Real Strategies data connector enables marketers to extract and combine data from multiple sources, such as Google Ads, Facebook Ads, and Instagram, just to name a few. With its user-friendly interface, you can effortlessly view and analyze data, track key performance indicators, and discover trends and patterns, all in one place.",
  "metrics": {
    "title": "What are the most popular metrics in Real Strategies to analyze?",
    "bullets": [
      {
        "title": "Click-Through Rates",
        "description": "Analyze the effectiveness of ad creatives and their ability to generate clicks"
      },
      {
        "title": "Impressions",
        "description": "Evaluate the visibility and reach of your ads"
      },
      {
        "title": "Conversion Rate",
        "description": "Measure the effectiveness of your campaigns in driving conversions"
      },
      {
        "title": "Cost per Acquisition",
        "description": "Calculate the average cost of acquiring a new customer"
      },
      {
        "title": "Return on Ad Spend",
        "description": "Assess the profitability of your advertising investments"
      },
      {
        "title": "Engagement Rate",
        "description": "Monitor the level of interaction and engagement with your content"
      },
      {
        "title": "Website Traffic",
        "description": "Track the number of visitors coming to your website"
      }
    ]
  },
  "reasons": {
    "title": "Why analyze Real Strategies?",
    "bullets": [
      {
        "title": "Targeted Advertising",
        "description": "Deliver personalized ads to specific audience segments for higher engagement"
      },
      {
        "title": "Optimize Campaign Performance",
        "description": "Identify underperforming campaigns and make data-driven adjustments"
      },
      {
        "title": "Track ROI",
        "description": "Measure the return on investment for your marketing efforts"
      },
      {
        "title": "Improve Decision-Making",
        "description": "Make informed decisions based on real-time marketing data"
      },
      {
        "title": "Enhance Customer Experience",
        "description": "Tailor marketing strategies to meet the preferences and needs of your audience"
      },
      {
        "title": "Stay Ahead of Competitors",
        "description": "Leverage data insights to outperform your competitors in the digital landscape"
      }
    ]
  }
}